graphene_permissions2/__init__.py
graphene_permissions2/mixins.py
graphene_permissions2/permissions.py
graphene_permissions2-1.2.1.dist-info/LICENSE.txt
graphene_permissions2-1.2.1.dist-info/METADATA
graphene_permissions2-1.2.1.dist-info/WHEEL
graphene_permissions2-1.2.1.dist-info/top_level.txt
graphene_permissions2-1.2.1.dist-info/RECORD
