Metadata-Version: 2.1
Name: graphene-permissions2
Version: 1.2.1
Summary: Simple graphene-django permission system.
Home-page: https://github.com/vintersnow/graphene-permissions
Author: vintersnow
License: MIT
Keywords: graphene django permissions permission system
Classifier: Development Status :: 5 - Production/Stable
Classifier: Operating System :: OS Independent
Classifier: Programming Language :: Python :: 3
Classifier: Programming Language :: Python :: 3.10
Classifier: Environment :: Web Environment
Classifier: Framework :: Django :: 3.0
Classifier: Framework :: Django :: 4.0
Classifier: Topic :: Internet :: WWW/HTTP
Classifier: Intended Audience :: Developers
Requires-Python: >=3.10
License-File: LICENSE.txt
Requires-Dist: django-filter
Requires-Dist: graphene
Requires-Dist: graphene-django
